mongo_sql_parser/__init__.py
mongo_sql_parser/mongo_filter_parser.py
mongo_sql_parser/mongo_shell_parser.py
mongo_sql_parser/mongodb_validator.py
mongo_sql_parser/sql_mongo_parser.py
mongo_sql_parser-0.1.0.dist-info/licenses/LICENSE
mongo_sql_parser-0.1.0.dist-info/METADATA
mongo_sql_parser-0.1.0.dist-info/WHEEL
mongo_sql_parser-0.1.0.dist-info/top_level.txt
mongo_sql_parser-0.1.0.dist-info/RECORD
